{
    "Ar36": {
        "error": 0.0009076594767982247,
        "error_type": "SEM",
        "filter_outliers_dict": {
            "filter_outliers": true,
            "iterations": 2,
            "std_devs": 2
        },
        "fit": "parabolic",
        "value": 0.1391653192962572
    },
    "Ar37": {
        "error": 0.013506254562846967,
        "error_type": "SEM",
        "filter_outliers_dict": {
            "filter_outliers": true,
            "iterations": 2,
            "std_devs": 2
        },
        "fit": "linear",
        "value": 0.2726225611374252
    },
    "Ar38": {
        "error": 0.005234117168520841,
        "error_type": "SEM",
        "filter_outliers_dict": {
            "filter_outliers": true,
            "iterations": 2,
            "std_devs": 2
        },
        "fit": "linear",
        "value": 1.204284780214911
    },
    "Ar39": {
        "error": 0.0159186387193505,
        "error_type": "SEM",
        "filter_outliers_dict": {
            "filter_outliers": true,
            "iterations": 2,
            "std_devs": 2
        },
        "fit": "parabolic",
        "value": 31.63520893594347
    },
    "Ar40": {
        "error": 0.03535440350275041,
        "error_type": "SEM",
        "filter_outliers_dict": {
            "filter_outliers": true,
            "iterations": 2,
            "std_devs": 2
        },
        "fit": "parabolic",
        "value": 137.6008514852876
    }
}