{
    "Ar36": {
        "error": 0.00047114436435770763,
        "error_type": "SEM",
        "filter_outliers_dict": {
            "filter_outliers": true,
            "iterations": 2,
            "std_devs": 2
        },
        "fit": "parabolic",
        "value": 0.037572659565793226
    },
    "Ar37": {
        "error": 0.014699119542709046,
        "error_type": "SEM",
        "filter_outliers_dict": {
            "filter_outliers": true,
            "iterations": 2,
            "std_devs": 2
        },
        "fit": "linear",
        "value": -0.030615869636817818
    },
    "Ar38": {
        "error": 0.00501123963982542,
        "error_type": "SEM",
        "filter_outliers_dict": {
            "filter_outliers": true,
            "iterations": 2,
            "std_devs": 2
        },
        "fit": "linear",
        "value": 0.007697284590081522
    },
    "Ar39": {
        "error": 0.013458888103229542,
        "error_type": "SEM",
        "filter_outliers_dict": {
            "filter_outliers": true,
            "iterations": 2,
            "std_devs": 2
        },
        "fit": "parabolic",
        "value": 6.26200671220044
    },
    "Ar40": {
        "error": 0.02573263569562686,
        "error_type": "SEM",
        "filter_outliers_dict": {
            "filter_outliers": true,
            "iterations": 2,
            "std_devs": 2
        },
        "fit": "parabolic",
        "value": 30.60339371339502
    }
}